[1,0,0,[["cc.JsonAsset",["_name","json"],1]],[[0,0,1,3]],[[0,"levels",{"1":{"colors":"RGCB","moves":18,"score":155000,"bossLife":0,"bossName":"","bossColor":"","bombExplodeMoves":0,"ribbonsMovesForDrop":3,"revision":"3eeb96701d19462bfb1f4f40c867a335","map":["  k.l.b "," T.....T"," T.....T","  ..... ","  RyRyR "," QqRyRqQ"," QRyRyRQ","  qRхRq "],"floorAttribute":["00000000","00000000","00000000","00000000","00101010","00010100","00101010","00010100"],"decorators":["........","........","........","........","........","........","........","........"],"cellAttribute":["........","........","........","........","........","........","........","........"],"addMovesAmount":[],"ribbonsMoves":[],"task":[{"type":"CollectColor","cell":"B","amount":"120"},{"type":"CollectBlackberry","cell":"Z","amount":"15"},{"type":"CollectComplexTask","parts":"bkl","taskName":"snowman"}]},"2":{"colors":"RGCY","moves":31,"score":155000,"bossLife":0,"bossName":"","bossColor":"","bombExplodeMoves":0,"ribbonsMovesForDrop":3,"revision":"a9c7d81950c4829c35ea16874cde0ba9","map":[" ..  .. ","...  ...","........","........","IIzzzzII","IIxxxxII"," vvvvvv ","  mmmm  "],"floorAttribute":["00000000","00000000","00000000","00000000","00000000","00000000","00000000","00000000"],"decorators":["........","........","........","........","........","........","........","........"],"cellAttribute":["........","........","........","........","........","........","........","........"],"addMovesAmount":[],"ribbonsMoves":[],"task":[{"type":"CollectColor","cell":"Y","amount":"120"},{"type":"CollectPearl","cell":"m","amount":"18"},{"type":"CollectType","cell":"I","amount":"2"}]},"3":{"colors":"RGACB","moves":26,"score":105000,"bossLife":0,"bossName":"","bossColor":"R","bombExplodeMoves":0,"ribbonsMovesForDrop":3,"bombRibbonsProbablity":0,"revision":"23e67375d98dc4bcc639692fc223de7e","map":[" ...... ","........","........","........","........","........","........"," ...... "],"floorAttribute":["01000000","10100000","01010000","00101000","00010100","00001010","00000101","00000010"],"decorators":["........",".G....R.","..*]....","..]*]...","...]*]..","....]*..",".C....A.","........"],"cellAttribute":["........",".*....*.","..**....","..***...","...***..","....**..",".*....*.","........"],"addMovesAmount":[],"ribbonsMoves":[],"task":[{"type":"CollectColor","cell":"B","amount":"70"},{"type":"ClearCellAttributes"},{"type":"CollectType","decorator":"mouse","amount":"auto"}]},"4":{"colors":"GACOY","moves":23,"score":95000,"bossLife":12,"bossName":"kitty","bossColor":"","bombExplodeMoves":0,"ribbonsMovesForDrop":3,"revision":"cb26a21cd75b5ff5f430e55043fef763","map":["j......j","........","........","........","........"," ...... ","  jaaj  ","  .aa.  "],"floorAttribute":["00000000","00000000","00000000","00000000","30000003","00000000","00000000","00300300"],"decorators":[".*....*.","........",".*....*.","........",".*....*.","........","........","........"],"cellAttribute":[".f....f.",".f....f.",".f....f.",".f....f.",".f....f.",".f....f.","........","........"],"addMovesAmount":[],"ribbonsMoves":[],"task":[{"type":"CollectColor","cell":"Y","amount":"60"},{"type":"CollectType","cell":"j","amount":"4"},{"type":"CollectType","cell":"a","amount":"auto"}]},"5":{"colors":"RGACY","moves":28,"score":95000,"bossLife":0,"bossName":"","bossColor":"","bombExplodeMoves":0,"ribbonsMovesForDrop":3,"bombRibbonsProbablity":0,"revision":"98c94082f52af3a7bb8f7420f382c185","map":["....... ","........","..II....","..II....","........","........","........"," ......."],"floorAttribute":["22220000","22222000","22002200","22002200","02222200","00222200","00000000","00000000"],"decorators":["...*....",".*..Y...","....Y...","*...Y...",".YYYY...","........","........","........"],"cellAttribute":["........","........","........","........","........","........","........","........"],"addMovesAmount":[],"ribbonsMoves":[],"task":[{"type":"CollectColor","cell":"Y","amount":"50"},{"type":"CollectType","cell":"I","amount":"1"},{"type":"ClearFloorAttributes","cell":2,"amount":"26"}]},"6":{"colors":"GACP","moves":23,"score":130000,"bossLife":0,"bossName":"","bossColor":"","bombExplodeMoves":0,"ribbonsMovesForDrop":4,"revision":"d361d0195adbeea75068ad5ee0a26027","map":[" .....  "," . . .  "," .A.P.  "," A. .P  ","..A.P.. ","....... ",".rrrrr. "," . . .  "],"floorAttribute":["04444400","00000000","00000000","00000000","00000000","00000000","00000000","00000000"],"decorators":["........","........","........","........","##...##.","#######.","#.....#.",".].].].."],"cellAttribute":["........","........","........","........","........","........","........","........"],"addMovesAmount":[],"ribbonsMoves":[],"task":[{"type":"CollectColor","cell":"P","amount":"75"},{"type":"CollectType","decorator":"mouse","amount":"auto"},{"type":"FillCarpet"}]},"7":{"colors":"GCPW","moves":26,"score":230000,"bossLife":0,"bossName":"","bossColor":"R","bombExplodeMoves":0,"ribbonsMovesForDrop":3,"bombRibbonsProbablity":0,"revision":"dab1ec76219214fe9b9ec65ceee83f59","map":["  w.w   "," 4...4  ","4.....4 "," .....  "," .....  ","4.....4 "," 4...4  ","  w.w   "],"floorAttribute":["00000000","00000000","00000000","00000000","00000000","00000000","00000000","00000000"],"decorators":["...P....","..P.P...","........","........","........","........","..P.P...","...P...."],"cellAttribute":["........","........","........","........","........","........","........","........"],"addMovesAmount":[],"ribbonsMoves":[],"task":[{"type":"CollectColor","cell":"P","amount":"90"},{"type":"CollectColor","cell":"W","amount":"120"},{"type":"CollectType","cell":4,"amount":"8"}]},"8":{"colors":"GCOB","moves":21,"score":135000,"bossLife":30,"bossName":"fox","bossColor":"","bombExplodeMoves":5,"ribbonsMovesForDrop":3,"revision":"8aafa5369fb004e4addcabe70ea5aad0","map":["  ....LL"," .....LL","..... ..",".... ...","... ....",".. .....","aa..... ","aa....  "],"floorAttribute":["00000000","00000000","00000000","00000000","00000000","00000000","00000000","00000000"],"decorators":["..].....","........","].].]...",".....]..","..].....","...].].]","........",".....].."],"cellAttribute":["........","........","........","........","........","........","........","........"],"addMovesAmount":[],"ribbonsMoves":[],"task":[{"type":"CollectColor","cell":"B","amount":"80"},{"type":"CollectType","decorator":"mouse","amount":"auto"},{"type":"CollectType","cell":"a","amount":"auto"}]},"9":{"colors":"RGACY","moves":27,"score":110000,"bossLife":0,"bossName":"","bossColor":"","bombExplodeMoves":0,"ribbonsMovesForDrop":3,"revision":"414f455e93c45ca556bdb7f338b146ac","map":["........","........","........","....М...","...@....","........","........","........"],"floorAttribute":["00000000","02222220","02200020","02220020","02222020","02222220","02222220","00000000"],"decorators":["........","..*.*.*.","..^.....","..^...*.","..^Y....","..^^^^*.","........","........"],"cellAttribute":["........","........","........","........","........","........","........","........"],"addMovesAmount":[],"ribbonsMoves":[],"task":[{"type":"CollectType","decorator":"mouse","amount":5},{"type":"CollectColor","cell":"Y","amount":"60"},{"type":"ClearFloorAttributes","cell":2,"amount":"30"}]},"10":{"colors":"RGCP","moves":21,"score":130000,"bossLife":30,"bossName":"panda","bossColor":"","bombExplodeMoves":0,"ribbonsMovesForDrop":4,"revision":"5d4f784e4b08e2adfe4170a028da633d","objects":[{"code":"FrozenObject","name":"butterfly","x":0,"y":0},{"code":"FrozenObject","name":"butterfly","x":6,"y":0},{"code":"FrozenObject","name":"butterfly","x":0,"y":6},{"code":"FrozenObject","name":"butterfly","x":3,"y":3},{"code":"FrozenObject","name":"butterfly","x":6,"y":6}],"map":["...  ...","........"," ...... "," ..aa.. "," ..aa.. "," .P.P.. ","...P....","...  ..."],"floorAttribute":["22200222","22200222","00000000","00022000","00022000","00000000","22200222","22200222"],"decorators":["###..###","###..###","........","........","........","........","###..###","###..###"],"cellAttribute":["........","........","........","........","........","........","........","........"],"addMovesAmount":[],"ribbonsMoves":[],"task":[{"type":"CollectColor","cell":"P","amount":"80"},{"type":"CollectType","cell":"a","amount":"auto"},{"type":"CollectObject","object":"FrozenObject","name":"butterfly"}]},"11":{"colors":"GCYP","moves":20,"score":210000,"bossLife":0,"bossName":"","bossColor":"","bombExplodeMoves":0,"ribbonsMovesForDrop":5,"revision":"8ee540d7cbfafda4c2424f2c25514af9","map":["...  ...","...  ...","...  ...","...  ...","...  ...","...  ...","...  ...","...  ..."],"floorAttribute":["10100101","01000010","10100101","01000010","10100101","01000010","10100101","01000010"],"decorators":["........","........",".*....*.","*.*..*.*",".*....*.","*.*..*.*",".*....*.","*.*..*.*"],"cellAttribute":["........","........",".b....b.","b.b..b.b",".b....b.","b.b..b.b",".b....b.","b.b..b.b"],"addMovesAmount":[],"ribbonsMoves":[],"task":[{"type":"CollectColor","cell":"Y","amount":"85"},{"type":"CollectColor","cell":"P","amount":"85"},{"type":"ClearCellAttributes","cell":"b","amount":"24","attribute":"bird"}]},"12":{"colors":"RGCB","moves":34,"score":260000,"bossLife":0,"bossName":"","bossColor":"R","bombExplodeMoves":0,"ribbonsMovesForDrop":3,"revision":"37cef7386de123ed6c87b3f6b8efebcd","map":[".      .","..    ..","...  ...","...UU...","...UU...","...UU...","...UU...","M..UU..M"],"floorAttribute":["20000002","22000022","22200222","22222222","00022000","00022000","00022000","02222220"],"decorators":["........","*......*","**....**",".**..**.","........","........","........","........"],"cellAttribute":["........","........","........","........","........","........","........","........"],"addMovesAmount":[],"ribbonsMoves":[],"task":[{"type":"CollectColor","cell":"B","amount":"200"},{"type":"ClearFloorAttributes","cell":2,"amount":"32"},{"type":"CollectType","cell":"U","amount":"auto"}]},"13":{"colors":"RGACY","moves":33,"score":150000,"bossLife":25,"bossName":"piggy","bossColor":"","bombExplodeMoves":0,"ribbonsMovesForDrop":3,"candyContent":"q","revision":"bc9cfd9ad96c960acb4d7a78d7b6263f","map":[" ..;.;.;"," ...;.;."," ..;.;.;","r...;.;.","r..;.;.;","raa.....","raa.....","rrrrr   "],"floorAttribute":["01100000","01100000","01100000","01100000","01100000","01111111","01111111","00000000"],"decorators":["........","........","........","........","........","........","........","........"],"cellAttribute":["........","........","........","........","........","........","........","........"],"addMovesAmount":[],"ribbonsMoves":[],"task":[{"type":"CollectColor","cell":"Y","amount":"85"},{"type":"CollectType","cell":"r","amount":"22"},{"type":"CollectType","cell":"a","amount":"auto"}]},"14":{"colors":"GAP","moves":25,"score":185000,"bossLife":0,"bossName":"","bossColor":"R","bombExplodeMoves":0,"ribbonsMovesForDrop":3,"bombRibbonsProbablity":0,"revision":"1631e23d4b73ddfac546eab902475386","map":[" .   .  ",".U...U. ","..   .. ",".U. .U. "," .....  ",".U. .U. ","..   .. ",".U...U. "],"floorAttribute":["02000200","22202220","02000200","22202220","02000200","22202220","02000200","22202220"],"decorators":["........","........","........","........","........","........","........","........"],"cellAttribute":["........","........","........","........","........","........","........","........"],"addMovesAmount":[],"ribbonsMoves":[],"task":[{"type":"CollectColor","cell":"P","amount":"130"},{"type":"ClearFloorAttributes","cell":2,"amount":"32"},{"type":"CollectType","cell":"U","amount":"auto"}]},"15":{"colors":"RGAY","moves":23,"score":145000,"bossLife":25,"bossName":"angrybubble","bossColor":"","bombExplodeMoves":0,"ribbonsMovesForDrop":3,"bombRibbonsProbablity":0,"revision":"9d882b70fda6faf3a4fcedc1784a3ad2","map":["  ....  ","...aa...",". .aa. .","........","........","........","...  ...","...  ..."],"floorAttribute":["00000000","00000000","00000000","01000010","10100101","01000010","00000000","00000000"],"decorators":["........","........","........","........","........","bbb..bbb","bbb..bbb","bbb..bbb"],"cellAttribute":["........","........","........","........","........","***..***","***..***","***..***"],"addMovesAmount":[],"ribbonsMoves":[],"task":[{"type":"CollectColor","cell":"Y","amount":"85"},{"type":"ClearCellAttributes"},{"type":"CollectType","cell":"a","amount":"auto"}]},"16":{"colors":"RGACB","moves":29,"score":120000,"bossLife":0,"bossName":"","bossColor":"R","bombExplodeMoves":0,"ribbonsMovesForDrop":3,"revision":"984be19a23363e62c0752d7cca2ab294","map":["h......h","5......5","h......h","6......6","h......h","7......7","h......h","8......8"],"floorAttribute":["00010000","00001000","00010000","00001000","00010000","00001000","00010000","00001000"],"decorators":[".^....^.","*^....^*",".^....^.","*^....^*",".^....^.","*^....^*",".^....^.","*^....^*"],"cellAttribute":["........","........","........","........","........","........","........","........"],"addMovesAmount":[],"ribbonsMoves":[],"task":[{"type":"CollectColor","cell":"B","amount":"85"},{"type":"CollectMorphColor","cell":9,"amount":"8"},{"type":"CollectType","cell":"h","amount":"8"}]},"17":{"colors":"RGACOY","moves":30,"score":85000,"bossLife":0,"bossName":"","bossColor":"","bombExplodeMoves":0,"ribbonsMovesForDrop":3,"bombRibbonsProbablity":0,"revision":"b9ac09f2958c616db8a586b480d98ad6","map":["v.....v ","....... ","....... ","....... ","....... ","....... ","v.....v ","        "],"floorAttribute":["00000000","00303000","03000300","00030000","03000300","00303000","00000000","00000000"],"decorators":["..@.@...",".@...@..","@.....@.","........","@.....@.",".@...@..","..@.@...","........"],"cellAttribute":["..*.*...",".*...*..","*.....*.","........","*.....*.",".*...*..","..*.*...","........"],"addMovesAmount":[],"ribbonsMoves":[],"task":[{"type":"CollectColor","cell":"Y","amount":"50"},{"type":"CollectPearl","cell":"m","amount":"4"},{"type":"ClearCellAttributes"}]},"18":{"colors":"RGACB","moves":33,"score":140000,"bossLife":0,"bossName":"","bossColor":"","bombExplodeMoves":0,"ribbonsMovesForDrop":3,"bombRibbonsProbablity":0,"revision":"a7dcae697b1e6e93f8ef8c44cd02ff50","map":["х.......","........","...xxxxx","...rxxxr","...rrxrr","...rrxrr","...rxxxr","...xxxxx"],"floorAttribute":["01100000","11100000","11100000","00010001","00011011","00011011","00010001","00000000"],"decorators":["........","........","........","..*.....","..*.....","..*.....","..*.....","..*....."],"cellAttribute":["........","........","........","........","........","........","........","........"],"addMovesAmount":[],"ribbonsMoves":[],"task":[{"type":"CollectColor","cell":"B","amount":"80"},{"type":"CollectPearl","cell":"m","amount":"18"},{"type":"CollectType","cell":"r","amount":"12"}]},"19":{"colors":"RGACB","moves":30,"score":90000,"bossLife":0,"bossName":"","bossColor":"R","bombExplodeMoves":0,"ribbonsMovesForDrop":3,"revision":"d4b808b0ee1b060495d48ac540dbcb74","map":[" vv ....","v.......","v......."," .......","....... ",".......v",".......v",".... vv "],"floorAttribute":["00000000","02000220","00200220","00022000","00022000","02200200","02200020","00000000"],"decorators":[".....###",".....**#",".....**#","...**...","...**...","#**.....","#**.....","###....."],"cellAttribute":["........","........","........","........","........","........","........","........"],"addMovesAmount":[],"ribbonsMoves":[],"task":[{"type":"CollectColor","cell":"B","amount":"50"},{"type":"CollectPearl","cell":"m","amount":"8"},{"type":"ClearFloorAttributes","cell":2,"amount":"16"}]},"20":{"colors":"RGACW","moves":25,"score":80000,"bossLife":0,"bossName":"","bossColor":"","bombExplodeMoves":0,"ribbonsMovesForDrop":3,"bombRibbonsProbablity":0,"revision":"5fc09714ad8975522ad03f9b88cba509","map":["....... ","а.аха.а ","а.а.а.а ","....... ","....... ","....... ","....... ","....... "],"floorAttribute":["11111110","01010100","01010100","11111110","00000000","00000000","00000000","00000000"],"decorators":[".@.@.@..","........","........",".@.@.@..","........","........","........","........"],"cellAttribute":["........","........","........","........","........","........","........","ccccccc."],"addMovesAmount":[],"ribbonsMoves":[],"task":[{"type":"CollectColor","cell":"W","amount":"60"},{"type":"ClearCellAttributes","cell":"c","amount":"7","attribute":"croissant"},{"type":"CollectSnail"}]},"test":{"rand":83760}}]],0,0,[],[],[]]